README.rst
setup.py
cmutils/__init__.py
cmutils/email.py
cmutils/excel.py
cmutils/io.py
cmutils/log.py
cmutils/monitor.py
cmutils/system.py
cmutils/test.py
cmutils/value.py
cmutils.egg-info/PKG-INFO
cmutils.egg-info/SOURCES.txt
cmutils.egg-info/dependency_links.txt
cmutils.egg-info/requires.txt
cmutils.egg-info/top_level.txt